MANIFEST.in
pyproject.toml
setup.cfg
setup.py
rmopv2/__init__.py
rmopv2.egg-info/PKG-INFO
rmopv2.egg-info/SOURCES.txt
rmopv2.egg-info/dependency_links.txt
rmopv2.egg-info/entry_points.txt
rmopv2.egg-info/not-zip-safe
rmopv2.egg-info/requires.txt
rmopv2.egg-info/top_level.txt
rmopv2/conf/__init__.py
rmopv2/conf/global_settings.py
rmopv2/conf/app_template/__init__.py-tpl
rmopv2/conf/app_template/admin.py-tpl
rmopv2/conf/app_template/apps.py-tpl
rmopv2/conf/app_template/models.py-tpl
rmopv2/conf/app_template/tests.py-tpl
rmopv2/conf/app_template/views.py-tpl
rmopv2/conf/app_template/migrations/__init__.py-tpl
rmopv2/conf/demo2_template/sdk.py-tpl
rmopv2/conf/demo_template/demo.py-tpl
rmopv2/conf/makermop_template/templet1.py-tpl
rmopv2/conf/makermop_template/project_name/__init__.py-tpl
rmopv2/conf/makermop_template/project_name/makermop.py-tpl
rmopv2/conf/makermop_template/project_name/templete1.py-tpl
rmopv2/conf/makermop_template/project_name/templete2.py-tpl
rmopv2/conf/project_template/templet1.py-tpl
rmopv2/conf/project_template/project_name/__init__.py-tpl
rmopv2/conf/project_template/project_name/templete.py-tpl
rmopv2/conf/project_template/project_name/templete1.py-tpl
rmopv2/conf/project_template/project_name/templete2.py-tpl
rmopv2/core/__init__.py
rmopv2/core/exceptions.py
rmopv2/core/management/__init__.py
rmopv2/core/management/base.py
rmopv2/core/management/templates.py
rmopv2/core/management/commands/__init__.py
rmopv2/core/management/commands/demo.py
rmopv2/core/management/commands/demo2.py
rmopv2/core/management/commands/rmop.py
rmopv2/core/management/commands/startproject.py